{
  "schema_version": 1,
  "generated_at": "2026-06-10T18:49:59.632877458Z",
  "repository": "https://github.com/paulmeier/kasas-plugins",
  "plugins": [
    {
      "name": "coffee-budget",
      "version": "0.4.0",
      "description": "Labels transactions whose description matches a keyword (default: coffee).",
      "author": "kasas community",
      "license": "MIT",
      "homepage": "https://github.com/paulmeier/kasas-plugins/tree/main/plugins/coffee-budget",
      "runtime": "lua",
      "entrypoint": "main.lua",
      "hooks": [
        "OnTransactionCreate",
        "OnTransactionUpdate",
        "OnPageRender",
        "OnPageAction",
        "OnUninstall"
      ],
      "capabilities": [
        "transactions:read",
        "labels:write",
        "ui:page"
      ],
      "capability_tier": "write",
      "ui": {
        "title": "Coffee Budget",
        "icon": "coin"
      },
      "path": "plugins/coffee-budget",
      "files": [
        {
          "path": "README.md",
          "sha256": "b7d09dce10fbaaabf432d33f114008580e67f7155589c2178a2d6b9e7fcda5a9",
          "size": 1897
        },
        {
          "path": "main.lua",
          "sha256": "900c58950140e044a95f60f9cd2fa22f9f3ffb85a1e5307bd3bf7eea5fe53f21",
          "size": 4326
        },
        {
          "path": "plugin.toml",
          "sha256": "ae643396c0445c6ac37394312de9b30e57f9464a59f1128592b0ed6b99452b64",
          "size": 766
        }
      ],
      "content_hash": "sha256:f6f0674f92b45280d85d68441455c3121261a2b446556b88c32865b764bf76eb",
      "size_bytes": 6989
    },
    {
      "name": "double-charge-detector",
      "version": "0.1.0",
      "description": "Finds possible double charges: equal amounts at the same merchant within a configurable day window.",
      "author": "kasas community",
      "license": "MIT",
      "homepage": "https://github.com/paulmeier/kasas-plugins/tree/main/plugins/double-charge-detector",
      "runtime": "js",
      "entrypoint": "main.ts",
      "hooks": [
        "OnTransactionCreate",
        "OnPageRender",
        "OnPageAction",
        "OnUninstall"
      ],
      "capabilities": [
        "transactions:read",
        "extensions:write",
        "ui:page"
      ],
      "capability_tier": "write",
      "ui": {
        "title": "Double Charges",
        "icon": "flag"
      },
      "path": "plugins/double-charge-detector",
      "files": [
        {
          "path": "README.md",
          "sha256": "7ab1ad9117ae89325e4391a0c1d867f6cfbeb13bbc4e1ce52f9a44e15948b488",
          "size": 2572
        },
        {
          "path": "main.ts",
          "sha256": "90f405d3a26fa5c362a8a519942a3a8f81c34ba0548d503d102a3ac54f26412d",
          "size": 9359
        },
        {
          "path": "plugin.toml",
          "sha256": "6e088418185fe14d78b6d02ef6c600e7c5d7b69bc8a0da120f3eae7a28a960d0",
          "size": 1042
        }
      ],
      "content_hash": "sha256:0084f19e3ad478f80136b379fe3bbedf1448da37bf5a3e0dd18ffea37790634e",
      "size_bytes": 12973
    },
    {
      "name": "large-expense-alert",
      "version": "0.3.0",
      "description": "Flags transactions whose amount exceeds a configurable threshold.",
      "author": "kasas community",
      "license": "Apache-2.0",
      "homepage": "https://github.com/paulmeier/kasas-plugins/tree/main/plugins/large-expense-alert",
      "runtime": "js",
      "entrypoint": "main.ts",
      "hooks": [
        "OnTransactionCreate",
        "OnUninstall"
      ],
      "capabilities": [
        "transactions:read",
        "extensions:write"
      ],
      "capability_tier": "write",
      "path": "plugins/large-expense-alert",
      "files": [
        {
          "path": "README.md",
          "sha256": "dc81daea70f5a21997fe9f55a41520c9e3015d1709e75cd01b5d3705f6a099c1",
          "size": 1229
        },
        {
          "path": "main.ts",
          "sha256": "a465da5f7ee028ad3c5fcbd88586aea9ac22bd627ef77a55a14c34cccc013ca1",
          "size": 2288
        },
        {
          "path": "plugin.toml",
          "sha256": "4549cbc1c98ba205b22c7abd724e66a98d604f74812b5cc25c949b4fdc597481",
          "size": 609
        }
      ],
      "content_hash": "sha256:1a4bc9bc5de966ab481a5589f062d3fabf9fed86ee6cbd6a25621b0376f304cc",
      "size_bytes": 4126
    },
    {
      "name": "lodash-demo",
      "version": "0.1.0",
      "description": "Summarizes transactions using the bundled lodash library (ADR 0001 demo).",
      "author": "kasas community",
      "license": "MIT",
      "homepage": "https://github.com/paulmeier/kasas-plugins/tree/main/plugins/lodash-demo",
      "runtime": "js",
      "entrypoint": "main.js",
      "hooks": [
        "OnTransactionCreate",
        "OnUninstall"
      ],
      "capabilities": [
        "transactions:read",
        "extensions:write"
      ],
      "capability_tier": "write",
      "path": "plugins/lodash-demo",
      "files": [
        {
          "path": "README.md",
          "sha256": "c3bcc8ba43f89f5d66e80641c9cfd0d78ea6b392561dbaacf4604c64b668ebbb",
          "size": 1087
        },
        {
          "path": "main.js",
          "sha256": "8b8bb4783a1e78278abfaf18a1a60b26bd821d0129aa464d39febbd5611cadb9",
          "size": 37347
        },
        {
          "path": "plugin.toml",
          "sha256": "9d24850ea7195c11ba248410a1de5d72062406056282b36c2bf4eacaf71ac80a",
          "size": 824
        }
      ],
      "content_hash": "sha256:f0f2d027b28db3817b3e9159aaadeb235a384ae85cafed23103fabd318f9c65b",
      "size_bytes": 39258
    }
  ]
}
